lord_of_the_rings/__init__.py
lord_of_the_rings/client.py
lord_of_the_rings/constants.py
lord_of_the_rings/endpoints.py
lord_of_the_rings/session.py
lord_aubrey_of_the_rings-0.1.0.dist-info/LICENSE
lord_aubrey_of_the_rings-0.1.0.dist-info/METADATA
lord_aubrey_of_the_rings-0.1.0.dist-info/WHEEL
lord_aubrey_of_the_rings-0.1.0.dist-info/top_level.txt
lord_aubrey_of_the_rings-0.1.0.dist-info/RECORD
