Metadata-Version: 2.1
Name: lord-aubrey-of-the-rings
Version: 0.1.0
Summary: A micro lord of the rings sdk
Author-email: Chiemeka Alim <lord.chiemy@gmail.com>
License: Copyright (c) 2018 The Python Packaging Authority        
Project-URL: Homepage, https://github.com/iamlordaubrey/lotr_sdk
Project-URL: Bug Tracker, https://github.com/iamlordaubrey/lotr_sdk/issues
Project-URL: API, https://the-one-api.dev/
Keywords: sdk,lord of the rings,the one api
Classifier: Programming Language :: Python :: 3
Classifier: License :: OSI Approved :: MIT License
Classifier: Operating System :: OS Independent
Requires-Python: >=3.10
License-File: LICENSE
Requires-Dist: requests (>=2.28.*)
Provides-Extra: dev
Requires-Dist: pytest ; extra == 'dev'
